README.md
pyproject.toml
requirements.txt
setup.py
WafWebFinder.egg-info/PKG-INFO
WafWebFinder.egg-info/SOURCES.txt
WafWebFinder.egg-info/dependency_links.txt
WafWebFinder.egg-info/entry_points.txt
WafWebFinder.egg-info/requires.txt
WafWebFinder.egg-info/top_level.txt
webfinder/__init__.py
webfinder/__main__.py
webfinder/__meta__.py
webfinder/args.py
webfinder/config.py
webfinder/result_pattern.py
webfinder/webfinder.py
webfinder/resources/user_agents.txt
webfinder/resources/waf_headers.json
webfinder/util/__init__.py
webfinder/util/color.py
webfinder/util/database.py
webfinder/util/getter.py
webfinder/util/logger.py
webfinder/util/pathgetter.py
webfinder/util/process.py
webfinder/util/ssl.py
webfinder/util/tools.py