Metadata-Version: 2.4
Name: WafWebFinder
Version: 0.1.13
Summary: Automated web server (behind WAF) finder.
Author-email: "Helvio Junior (M4v3r1ck)" <helvio_junior@hotmail.com>
Maintainer-email: "Helvio Junior (M4v3r1ck)" <helvio_junior@hotmail.com>
Project-URL: Documentation, https://github.com/helviojunior/webfinder
Project-URL: Source, https://github.com/helviojunior/webfinder
Project-URL: Tracker, https://github.com/helviojunior/webfinder
Project-URL: Author, https://github.com/helviojunior
Keywords: web finder,WAF Bypass,development,red team
Classifier: Development Status :: 4 - Beta
Classifier: Environment :: Console
Classifier: Intended Audience :: System Administrators
Classifier: License :: OSI Approved :: GNU General Public License v3 (GPLv3)
Classifier: Natural Language :: English
Classifier: Operating System :: OS Independent
Classifier: Programming Language :: Python
Classifier: Programming Language :: Python :: 3
Classifier: Programming Language :: Python :: 3.9
Classifier: Programming Language :: Python :: 3.10
Classifier: Programming Language :: Python :: 3.11
Classifier: Programming Language :: Python :: 3.12
Classifier: Programming Language :: Python :: 3 :: Only
Classifier: Programming Language :: Python :: Implementation :: PyPy
Classifier: Topic :: Security
Classifier: Topic :: Utilities
Requires-Python: <4,>=3.9
Requires-Dist: colorama
Requires-Dist: requests>=2.23.0
Requires-Dist: requests[socks]
Requires-Dist: cryptography==41.0.4
Requires-Dist: pyOpenSSL==23.2.0
Requires-Dist: setuptools>=75.2.0
Requires-Dist: cffi>=1.17.1
